setup.py
src/system_cmd/__init__.py
src/system_cmd/interface.py
src/system_cmd/meat.py
src/system_cmd/structures.py
src/system_cmd/utils.py
src/system_cmd.egg-info/PKG-INFO
src/system_cmd.egg-info/SOURCES.txt
src/system_cmd.egg-info/dependency_links.txt
src/system_cmd.egg-info/entry_points.txt
src/system_cmd.egg-info/top_level.txt