Metadata-Version: 1.1
Name: system-cmd
Version: 1.0dev1
Summary: My wrappers for subprocess.POpen
Home-page: http://github.com/AndreaCensi/system_cmd
Author: Andrea Censi
Author-email: andrea@cds.caltech.edu
License: UNKNOWN
Download-URL: http://github.com/AndreaCensi/system_cmd/tarball/1.0dev1
Platform: UNKNOWN
Classifier: Development Status :: 4 - Beta
